{
    "臺股期貨": {
        "自營商": {
            "交易多方口數": 12840,
            "交易多方金額": 28197042,
            "交易空方口數": 13555,
            "交易空方金額": 29762101,
            "交易多空淨口數": -715,
            "交易多空淨額": -1565059,
            "未平倉多方口數": 9308,
            "未平倉多方金額": 20489017,
            "未平倉空方口數": 16383,
            "未平倉空方金額": 36079168,
            "未平倉淨口數": -7075,
            "未平倉多空淨額": -15590151
        },
        "投信": {
            "交易多方口數": 8,
            "交易多方金額": 17638,
            "交易空方口數": 19,
            "交易空方金額": 41826,
            "交易多空淨口數": -11,
            "交易多空淨額": -24188,
            "未平倉多方口數": 1335,
            "未平倉多方金額": 2943141,
            "未平倉空方口數": 27305,
            "未平倉空方金額": 60196603,
            "未平倉淨口數": -25970,
            "未平倉多空淨額": -57253462
        },
        "外資": {
            "交易多方口數": 41838,
            "交易多方金額": 91855644,
            "交易空方口數": 40315,
            "交易空方金額": 88518238,
            "交易多空淨口數": 1523,
            "交易多空淨額": 3337407,
            "未平倉多方口數": 79616,
            "未平倉多方金額": 175489553,
            "未平倉空方口數": 17359,
            "未平倉空方金額": 38246448,
            "未平倉淨口數": 62257,
            "未平倉多空淨額": 137243105
        }
    },
    "電子期貨": {
        "自營商": {
            "交易多方口數": 753,
            "交易多方金額": 1377146,
            "交易空方口數": 517,
            "交易空方金額": 945830,
            "交易多空淨口數": 236,
            "交易多空淨額": 431316,
            "未平倉多方口數": 398,
            "未平倉多方金額": 730794,
            "未平倉空方口數": 408,
            "未平倉空方金額": 749333,
            "未平倉淨口數": -10,
            "未平倉多空淨額": -18539
        },
        "投信": {
            "交易多方口數": 0,
            "交易多方金額": 0,
            "交易空方口數": 0,
            "交易空方金額": 0,
            "交易多空淨口數": 0,
            "交易多空淨額": 0,
            "未平倉多方口數": 49,
            "未平倉多方金額": 89993,
            "未平倉空方口數": 400,
            "未平倉空方金額": 734640,
            "未平倉淨口數": -351,
            "未平倉多空淨額": -644647
        },
        "外資": {
            "交易多方口數": 1523,
            "交易多方金額": 2786141,
            "交易空方口數": 1806,
            "交易空方金額": 3303506,
            "交易多空淨口數": -283,
            "交易多空淨額": -517365,
            "未平倉多方口數": 2111,
            "未平倉多方金額": 3877058,
            "未平倉空方口數": 361,
            "未平倉空方金額": 663013,
            "未平倉淨口數": 1750,
            "未平倉多空淨額": 3214045
        }
    },
    "金融期貨": {
        "自營商": {
            "交易多方口數": 228,
            "交易多方金額": 284800,
            "交易空方口數": 206,
            "交易空方金額": 257327,
            "交易多空淨口數": 22,
            "交易多空淨額": 27473,
            "未平倉多方口數": 191,
            "未平倉多方金額": 238877,
            "未平倉空方口數": 281,
            "未平倉空方金額": 351784,
            "未平倉淨口數": -90,
            "未平倉多空淨額": -112907
        },
        "投信": {
            "交易多方口數": 0,
            "交易多方金額": 0,
            "交易空方口數": 0,
            "交易空方金額": 0,
            "交易多空淨口數": 0,
            "交易多空淨額": 0,
            "未平倉多方口數": 10,
            "未平倉多方金額": 12524,
            "未平倉空方口數": 0,
            "未平倉空方金額": 0,
            "未平倉淨口數": 10,
            "未平倉多空淨額": 12524
        },
        "外資": {
            "交易多方口數": 762,
            "交易多方金額": 952142,
            "交易空方口數": 633,
            "交易空方金額": 790876,
            "交易多空淨口數": 129,
            "交易多空淨額": 161265,
            "未平倉多方口數": 726,
            "未平倉多方金額": 909194,
            "未平倉空方口數": 1827,
            "未平倉空方金額": 2288036,
            "未平倉淨口數": -1101,
            "未平倉多空淨額": -1378842
        }
    },
    "小型臺指期貨": {
        "自營商": {
            "交易多方口數": 10758,
            "交易多方金額": 5899193,
            "交易空方口數": 10145,
            "交易空方金額": 5566625,
            "交易多空淨口數": 613,
            "交易多空淨額": 332567,
            "未平倉多方口數": 19129,
            "未平倉多方金額": 10510393,
            "未平倉空方口數": 2964,
            "未平倉空方金額": 1622417,
            "未平倉淨口數": 16165,
            "未平倉多空淨額": 8887976
        },
        "投信": {
            "交易多方口數": 0,
            "交易多方金額": 0,
            "交易空方口數": 0,
            "交易空方金額": 0,
            "交易多空淨口數": 0,
            "交易多空淨額": 0,
            "未平倉多方口數": 82,
            "未平倉多方金額": 45194,
            "未平倉空方口數": 0,
            "未平倉空方金額": 0,
            "未平倉淨口數": 82,
            "未平倉多空淨額": 45194
        },
        "外資": {
            "交易多方口數": 38240,
            "交易多方金額": 20990079,
            "交易空方口數": 36970,
            "交易空方金額": 20291967,
            "交易多空淨口數": 1270,
            "交易多空淨額": 698112,
            "未平倉多方口數": 3866,
            "未平倉多方金額": 2130696,
            "未平倉空方口數": 871,
            "未平倉空方金額": 478984,
            "未平倉淨口數": 2995,
            "未平倉多空淨額": 1651712
        }
    },
    "臺灣50期貨": {
        "自營商": {
            "交易多方口數": 144,
            "交易多方金額": 119192,
            "交易空方口數": 151,
            "交易空方金額": 124993,
            "交易多空淨口數": -7,
            "交易多空淨額": -5801,
            "未平倉多方口數": 192,
            "未平倉多方金額": 159828,
            "未平倉空方口數": 204,
            "未平倉空方金額": 169818,
            "未平倉淨口數": -12,
            "未平倉多空淨額": -9990
        },
        "投信": {
            "交易多方口數": 0,
            "交易多方金額": 0,
            "交易空方口數": 0,
            "交易空方金額": 0,
            "交易多空淨口數": 0,
            "交易多空淨額": 0,
            "未平倉多方口數": 0,
            "未平倉多方金額": 0,
            "未平倉空方口數": 0,
            "未平倉空方金額": 0,
            "未平倉淨口數": 0,
            "未平倉多空淨額": 0
        },
        "外資": {
            "交易多方口數": 0,
            "交易多方金額": 0,
            "交易空方口數": 0,
            "交易空方金額": 0,
            "交易多空淨口數": 0,
            "交易多空淨額": 0,
            "未平倉多方口數": 0,
            "未平倉多方金額": 0,
            "未平倉空方口數": 0,
            "未平倉空方金額": 0,
            "未平倉淨口數": 0,
            "未平倉多空淨額": 0
        }
    },
    "股票期貨": {
        "自營商": {
            "交易多方口數": 12103,
            "交易多方金額": 2589535,
            "交易空方口數": 12870,
            "交易空方金額": 2347410,
            "交易多空淨口數": -767,
            "交易多空淨額": 242125,
            "未平倉多方口數": 14675,
            "未平倉多方金額": 2953160,
            "未平倉空方口數": 81712,
            "未平倉空方金額": 13179684,
            "未平倉淨口數": -67037,
            "未平倉多空淨額": -10226524
        },
        "投信": {
            "交易多方口數": 0,
            "交易多方金額": 0,
            "交易空方口數": 0,
            "交易空方金額": 0,
            "交易多空淨口數": 0,
            "交易多空淨額": 0,
            "未平倉多方口數": 0,
            "未平倉多方金額": 0,
            "未平倉空方口數": 0,
            "未平倉空方金額": 0,
            "未平倉淨口數": 0,
            "未平倉多空淨額": 0
        },
        "外資": {
            "交易多方口數": 27439,
            "交易多方金額": 7291236,
            "交易空方口數": 27915,
            "交易空方金額": 7320907,
            "交易多空淨口數": -476,
            "交易多空淨額": -29672,
            "未平倉多方口數": 25680,
            "未平倉多方金額": 8113296,
            "未平倉空方口數": 14204,
            "未平倉空方金額": 4116484,
            "未平倉淨口數": 11476,
            "未平倉多空淨額": 3996812
        }
    },
    "ETF期貨": {
        "自營商": {
            "交易多方口數": 592,
            "交易多方金額": 180990,
            "交易空方口數": 520,
            "交易空方金額": 151094,
            "交易多空淨口數": 72,
            "交易多空淨額": 29896,
            "未平倉多方口數": 962,
            "未平倉多方金額": 411183,
            "未平倉空方口數": 5436,
            "未平倉空方金額": 1771710,
            "未平倉淨口數": -4474,
            "未平倉多空淨額": -1360527
        },
        "投信": {
            "交易多方口數": 0,
            "交易多方金額": 0,
            "交易空方口數": 0,
            "交易空方金額": 0,
            "交易多空淨口數": 0,
            "交易多空淨額": 0,
            "未平倉多方口數": 2659,
            "未平倉多方金額": 1159786,
            "未平倉空方口數": 4154,
            "未平倉空方金額": 3117497,
            "未平倉淨口數": -1495,
            "未平倉多空淨額": -1957711
        },
        "外資": {
            "交易多方口數": 1371,
            "交易多方金額": 492844,
            "交易空方口數": 1444,
            "交易空方金額": 510582,
            "交易多空淨口數": -73,
            "交易多空淨額": -17739,
            "未平倉多方口數": 4538,
            "未平倉多方金額": 2961698,
            "未平倉空方口數": 802,
            "未平倉空方金額": 224312,
            "未平倉淨口數": 3736,
            "未平倉多空淨額": 2737386
        }
    },
    "櫃買指數期貨": {
        "自營商": {
            "交易多方口數": 5,
            "交易多方金額": 2845,
            "交易空方口數": 11,
            "交易空方金額": 6290,
            "交易多空淨口數": -6,
            "交易多空淨額": -3445,
            "未平倉多方口數": 12,
            "未平倉多方金額": 6859,
            "未平倉空方口數": 0,
            "未平倉空方金額": 0,
            "未平倉淨口數": 12,
            "未平倉多空淨額": 6859
        },
        "投信": {
            "交易多方口數": 0,
            "交易多方金額": 0,
            "交易空方口數": 0,
            "交易空方金額": 0,
            "交易多空淨口數": 0,
            "交易多空淨額": 0,
            "未平倉多方口數": 11,
            "未平倉多方金額": 6290,
            "未平倉空方口數": 0,
            "未平倉空方金額": 0,
            "未平倉淨口數": 11,
            "未平倉多空淨額": 6290
        },
        "外資": {
            "交易多方口數": 0,
            "交易多方金額": 0,
            "交易空方口數": 0,
            "交易空方金額": 0,
            "交易多空淨口數": 0,
            "交易多空淨額": 0,
            "未平倉多方口數": 0,
            "未平倉多方金額": 0,
            "未平倉空方口數": 30,
            "未平倉空方金額": 17154,
            "未平倉淨口數": -30,
            "未平倉多空淨額": -17154
        }
    },
    "非金電期貨": {
        "自營商": {
            "交易多方口數": 72,
            "交易多方金額": 91165,
            "交易空方口數": 58,
            "交易空方金額": 73396,
            "交易多空淨口數": 14,
            "交易多空淨額": 17769,
            "未平倉多方口數": 118,
            "未平倉多方金額": 150117,
            "未平倉空方口數": 134,
            "未平倉空方金額": 170472,
            "未平倉淨口數": -16,
            "未平倉多空淨額": -20355
        },
        "投信": {
            "交易多方口數": 0,
            "交易多方金額": 0,
            "交易空方口數": 0,
            "交易空方金額": 0,
            "交易多空淨口數": 0,
            "交易多空淨額": 0,
            "未平倉多方口數": 1,
            "未平倉多方金額": 1272,
            "未平倉空方口數": 0,
            "未平倉空方金額": 0,
            "未平倉淨口數": 1,
            "未平倉多空淨額": 1272
        },
        "外資": {
            "交易多方口數": 39,
            "交易多方金額": 49377,
            "交易空方口數": 34,
            "交易空方金額": 43072,
            "交易多空淨口數": 5,
            "交易多空淨額": 6305,
            "未平倉多方口數": 11,
            "未平倉多方金額": 13994,
            "未平倉空方口數": 5,
            "未平倉空方金額": 6361,
            "未平倉淨口數": 6,
            "未平倉多空淨額": 7633
        }
    },
    "東證期貨": {
        "自營商": {
            "交易多方口數": 412,
            "交易多方金額": 133596,
            "交易空方口數": 483,
            "交易空方金額": 156602,
            "交易多空淨口數": -71,
            "交易多空淨額": -23006,
            "未平倉多方口數": 276,
            "未平倉多方金額": 89565,
            "未平倉空方口數": 313,
            "未平倉空方金額": 101571,
            "未平倉淨口數": -37,
            "未平倉多空淨額": -12006
        },
        "投信": {
            "交易多方口數": 0,
            "交易多方金額": 0,
            "交易空方口數": 0,
            "交易空方金額": 0,
            "交易多空淨口數": 0,
            "交易多空淨額": 0,
            "未平倉多方口數": 0,
            "未平倉多方金額": 0,
            "未平倉空方口數": 0,
            "未平倉空方金額": 0,
            "未平倉淨口數": 0,
            "未平倉多空淨額": 0
        },
        "外資": {
            "交易多方口數": 215,
            "交易多方金額": 69680,
            "交易空方口數": 156,
            "交易空方金額": 50573,
            "交易多空淨口數": 59,
            "交易多空淨額": 19108,
            "未平倉多方口數": 175,
            "未平倉多方金額": 56759,
            "未平倉空方口數": 120,
            "未平倉空方金額": 38930,
            "未平倉淨口數": 55,
            "未平倉多空淨額": 17829
        }
    },
    "印度50期貨-已下市": {
        "自營商": {
            "交易多方口數": 0,
            "交易多方金額": 0,
            "交易空方口數": 1,
            "交易空方金額": 590,
            "交易多空淨口數": -1,
            "交易多空淨額": -590,
            "未平倉多方口數": 30,
            "未平倉多方金額": 17552,
            "未平倉空方口數": 0,
            "未平倉空方金額": 0,
            "未平倉淨口數": 30,
            "未平倉多空淨額": 17552
        },
        "投信": {
            "交易多方口數": 0,
            "交易多方金額": 0,
            "交易空方口數": 0,
            "交易空方金額": 0,
            "交易多空淨口數": 0,
            "交易多空淨額": 0,
            "未平倉多方口數": 0,
            "未平倉多方金額": 0,
            "未平倉空方口數": 0,
            "未平倉空方金額": 0,
            "未平倉淨口數": 0,
            "未平倉多空淨額": 0
        },
        "外資": {
            "交易多方口數": 0,
            "交易多方金額": 0,
            "交易空方口數": 0,
            "交易空方金額": 0,
            "交易多空淨口數": 0,
            "交易多空淨額": 0,
            "未平倉多方口數": 0,
            "未平倉多方金額": 0,
            "未平倉空方口數": 0,
            "未平倉空方金額": 0,
            "未平倉淨口數": 0,
            "未平倉多空淨額": 0
        }
    },
    "美國標普500期貨": {
        "自營商": {
            "交易多方口數": 86,
            "交易多方金額": 50037,
            "交易空方口數": 76,
            "交易空方金額": 44204,
            "交易多空淨口數": 10,
            "交易多空淨額": 5834,
            "未平倉多方口數": 450,
            "未平倉多方金額": 262412,
            "未平倉空方口數": 89,
            "未平倉空方金額": 51957,
            "未平倉淨口數": 361,
            "未平倉多空淨額": 210455
        },
        "投信": {
            "交易多方口數": 0,
            "交易多方金額": 0,
            "交易空方口數": 0,
            "交易空方金額": 0,
            "交易多空淨口數": 0,
            "交易多空淨額": 0,
            "未平倉多方口數": 0,
            "未平倉多方金額": 0,
            "未平倉空方口數": 0,
            "未平倉空方金額": 0,
            "未平倉淨口數": 0,
            "未平倉多空淨額": 0
        },
        "外資": {
            "交易多方口數": 131,
            "交易多方金額": 76101,
            "交易空方口數": 98,
            "交易空方金額": 56928,
            "交易多空淨口數": 33,
            "交易多空淨額": 19174,
            "未平倉多方口數": 123,
            "未平倉多方金額": 71759,
            "未平倉空方口數": 4,
            "未平倉空方金額": 2331,
            "未平倉淨口數": 119,
            "未平倉多空淨額": 69428
        }
    },
    "美國道瓊期貨": {
        "自營商": {
            "交易多方口數": 303,
            "交易多方金額": 160605,
            "交易空方口數": 519,
            "交易空方金額": 275071,
            "交易多空淨口數": -216,
            "交易多空淨額": -114465,
            "未平倉多方口數": 2819,
            "未平倉多方金額": 1495922,
            "未平倉空方口數": 314,
            "未平倉空方金額": 166654,
            "未平倉淨口數": 2505,
            "未平倉多空淨額": 1329268
        },
        "投信": {
            "交易多方口數": 0,
            "交易多方金額": 0,
            "交易空方口數": 0,
            "交易空方金額": 0,
            "交易多空淨口數": 0,
            "交易多空淨額": 0,
            "未平倉多方口數": 0,
            "未平倉多方金額": 0,
            "未平倉空方口數": 0,
            "未平倉空方金額": 0,
            "未平倉淨口數": 0,
            "未平倉多空淨額": 0
        },
        "外資": {
            "交易多方口數": 671,
            "交易多方金額": 355603,
            "交易空方口數": 719,
            "交易空方金額": 381075,
            "交易多空淨口數": -48,
            "交易多空淨額": -25471,
            "未平倉多方口數": 1181,
            "未平倉多方金額": 626698,
            "未平倉空方口數": 0,
            "未平倉空方金額": 0,
            "未平倉淨口數": 1181,
            "未平倉多空淨額": 626698
        }
    }
}